jscraper/CredentialManager.py
jscraper/JobScraper.py
jscraper/__init__.py
jscraper/main.py
jscraper-0.1.2.dist-info/LICENSE
jscraper-0.1.2.dist-info/METADATA
jscraper-0.1.2.dist-info/WHEEL
jscraper-0.1.2.dist-info/entry_points.txt
jscraper-0.1.2.dist-info/RECORD
